vc2_conformance/__init__.py
vc2_conformance/codec_features.py
vc2_conformance/color_conversion.py
vc2_conformance/constraint_table.py
vc2_conformance/dimensions_and_depths.py
vc2_conformance/file_format.py
vc2_conformance/fixeddict.py
vc2_conformance/level_constraints.csv
vc2_conformance/level_constraints.py
vc2_conformance/level_sequence_restrictions.csv
vc2_conformance/picture_generators.py
vc2_conformance/py2x_compat.py
vc2_conformance/string_formatters.py
vc2_conformance/string_utils.py
vc2_conformance/symbol_re.py
vc2_conformance/version.py
vc2_conformance/version_constraints.py
vc2_conformance/bitstream/__init__.py
vc2_conformance/bitstream/exceptions.py
vc2_conformance/bitstream/exp_golomb.py
vc2_conformance/bitstream/io.py
vc2_conformance/bitstream/metadata.py
vc2_conformance/bitstream/serdes.py
vc2_conformance/bitstream/vc2.py
vc2_conformance/bitstream/vc2_autofill.py
vc2_conformance/bitstream/vc2_fixeddicts.py
vc2_conformance/decoder/__init__.py
vc2_conformance/decoder/assertions.py
vc2_conformance/decoder/exceptions.py
vc2_conformance/decoder/fragment_syntax.py
vc2_conformance/decoder/io.py
vc2_conformance/decoder/picture_syntax.py
vc2_conformance/decoder/sequence_header.py
vc2_conformance/decoder/stream.py
vc2_conformance/decoder/transform_data_syntax.py
vc2_conformance/encoder/__init__.py
vc2_conformance/encoder/exceptions.py
vc2_conformance/encoder/pictures.py
vc2_conformance/encoder/sequence.py
vc2_conformance/encoder/sequence_header.py
vc2_conformance/pseudocode/__init__.py
vc2_conformance/pseudocode/arrays.py
vc2_conformance/pseudocode/metadata.py
vc2_conformance/pseudocode/offsetting.py
vc2_conformance/pseudocode/parse_code_functions.py
vc2_conformance/pseudocode/picture_decoding.py
vc2_conformance/pseudocode/picture_encoding.py
vc2_conformance/pseudocode/quantization.py
vc2_conformance/pseudocode/slice_sizes.py
vc2_conformance/pseudocode/state.py
vc2_conformance/pseudocode/vc2_math.py
vc2_conformance/pseudocode/video_parameters.py
vc2_conformance-1.0.1.dist-info/LICENSE.txt
vc2_conformance-1.0.1.dist-info/METADATA
vc2_conformance-1.0.1.dist-info/WHEEL
vc2_conformance-1.0.1.dist-info/entry_points.txt
vc2_conformance-1.0.1.dist-info/top_level.txt
vc2_conformance-1.0.1.dist-info/RECORD
