Metadata-Version: 2.1
Name: vc2-conformance
Version: 1.0.1
Summary: Conformance testing utilities for the VC-2 video codec.
Home-page: https://github.com/bbc/vc2_conformance
Author: BBC R&D
License: GPL-3.0-only
Keywords: vc2 dirac dirac-pro conformance
Platform: UNKNOWN
Classifier: Development Status :: 5 - Production/Stable
Classifier: Intended Audience :: Developers
Classifier: Intended Audience :: Manufacturing
Classifier: Intended Audience :: Information Technology
Classifier: Intended Audience :: Telecommunications Industry
Classifier: License :: OSI Approved :: GNU General Public License v3 (GPLv3)
Classifier: Operating System :: POSIX :: Linux
Classifier: Operating System :: Microsoft :: Windows
Classifier: Operating System :: MacOS
Classifier: Programming Language :: Python :: 2
Classifier: Programming Language :: Python :: 2.7
Classifier: Programming Language :: Python :: 3
Classifier: Programming Language :: Python :: 3.6
Classifier: Programming Language :: Python :: 3.7
Classifier: Programming Language :: Python :: 3.8
Classifier: Programming Language :: Python :: 3.9
Requires-Dist: bitarray-hardbyte
Requires-Dist: sentinels
Requires-Dist: vc2-data-tables (<2.0,>=0.1.1)
Requires-Dist: vc2-bit-widths (<2.0,>=0.1.1)
Requires-Dist: vc2-conformance-data (<2.0,>=0.1.1)
Requires-Dist: pillow (<7) ; python_version < "3.0"
Requires-Dist: numpy (<1.17) ; python_version < "3.0"
Requires-Dist: enum34 ; python_version < "3.4"
Requires-Dist: pillow ; python_version >= "3.0"
Requires-Dist: numpy (<1.20) ; python_version >= "3.0" and python_version < "3.7"
Requires-Dist: numpy ; python_version >= "3.7"
